shmqueue3/__init__.py
shmqueue3/_version.py
shmqueue3/shmqueue3.py
shmqueue3/shmqueue3_test.py
shmqueue3-0.9.1.dist-info/licenses/LICENSE
shmqueue3-0.9.1.dist-info/METADATA
shmqueue3-0.9.1.dist-info/WHEEL
shmqueue3-0.9.1.dist-info/top_level.txt
shmqueue3-0.9.1.dist-info/RECORD
